didlogic_mcp/__init__.py
didlogic_mcp/__main__.py
didlogic_mcp/auth.py
didlogic_mcp/server.py
didlogic_mcp/prompts/__init__.py
didlogic_mcp/prompts/balance.py
didlogic_mcp/prompts/sipaccounts.py
didlogic_mcp/tools/__init__.py
didlogic_mcp/tools/allowed_ips.py
didlogic_mcp/tools/balance.py
didlogic_mcp/tools/base.py
didlogic_mcp/tools/calls.py
didlogic_mcp/tools/purchase.py
didlogic_mcp/tools/purchases.py
didlogic_mcp/tools/sip_accounts.py
didlogic_mcp/tools/transactions.py
didlogic_mcp-1.0.4.dist-info/METADATA
didlogic_mcp-1.0.4.dist-info/WHEEL
didlogic_mcp-1.0.4.dist-info/entry_points.txt
didlogic_mcp-1.0.4.dist-info/licenses/LICENSE
didlogic_mcp-1.0.4.dist-info/RECORD
