Metadata-Version: 2.4
Name: didlogic_mcp
Version: 1.0.4
Summary: DIDLogic MCP server
Author-email: Konstantin Tumalevich <userad@gmail.com>
License-Expression: MIT
License-File: LICENSE
Requires-Python: >=3.13
Requires-Dist: httpx>=0.28.1
Requires-Dist: mcp>=1.16.0
Requires-Dist: pydantic-settings>=2.8.1
Requires-Dist: pydantic>=2.10.6
